ipeakoin_sdk/__init__.py
ipeakoin_sdk/api_exception.py
ipeakoin_sdk/client.py
ipeakoin_sdk/request.py
ipeakoin_sdk/constant/Constant.py
ipeakoin_sdk/constant/__init__.py
ipeakoin_sdk/models/__init__.py
ipeakoin_sdk/models/api_response.py
ipeakoin_sdk/models/test_data.py
test/__init__.py
ipeakoin_sdk-0.0.1.dist-info/LICENSE
ipeakoin_sdk-0.0.1.dist-info/METADATA
ipeakoin_sdk-0.0.1.dist-info/WHEEL
ipeakoin_sdk-0.0.1.dist-info/top_level.txt
ipeakoin_sdk-0.0.1.dist-info/RECORD
